llm_mindmeld-0.2.0.dist-info/METADATA
llm_mindmeld-0.2.0.dist-info/WHEEL
llm_mindmeld-0.2.0.dist-info/entry_points.txt
llm_mindmeld-0.2.0.dist-info/licenses/LICENSE
mindmeld/__init__.py
mindmeld/eval.py
mindmeld/inference.py
mindmeld/metrics/__init__.py
mindmeld/metrics/answer_relevance.py
mindmeld/metrics/answer_similarity.py
mindmeld/metrics/echo.py
mindmeld/metrics/faithfulness.py
mindmeld/metrics/llm_judge.py
mindmeld/metrics/shorten_prompt_length.py
mindmeld/optimize.py
mindmeld/pydantic_utils.py
mindmeld/runner.py
mindmeld/synthetic.py
llm_mindmeld-0.2.0.dist-info/RECORD
