Metadata-Version: 2.1
Name: llm_mindmeld
Version: 0.2.0
Summary: A framework to glue all your AI tools together
Author-Email: Todd Cullen <todd@100-x.ai>
License: MIT
Requires-Python: >=3.11
Requires-Dist: pydantic>=2.9.2
Requires-Dist: instructor>=1.5.0
Requires-Dist: numpy>=2.1.1
Requires-Dist: sentence-transformers>=3.1.1
Requires-Dist: litellm>=1.51.3
Requires-Dist: pytest>=8.3.3
Requires-Dist: flake8>=7.1.1
